MANIFEST.in
README.md
setup.cfg
setup.py
kwick/__init__.py
kwick/__main__.py
kwick/kwick.py
kwickmapi_python.egg-info/PKG-INFO
kwickmapi_python.egg-info/SOURCES.txt
kwickmapi_python.egg-info/dependency_links.txt
kwickmapi_python.egg-info/requires.txt
kwickmapi_python.egg-info/top_level.txt
test/test_mapi.py