Metadata-Version: 1.1
Name: kwickmapi-python
Version: 1.1.3
Summary: A python library for kwick.de based on their mapi
Home-page: https://github.com/bloodywing/kwickmapi-python
Author: Bloodywing
Author-email: bloodywing@tastyespresso.de
License: GPL 3.0
Keywords: kwick,api,socialmedia,website,library
Platform: UNKNOWN
Requires: requests
